lkfmt/__init__.py
lkfmt/__main__.py
lkfmt/diff.py
lkfmt/formatter.py
lkfmt-0.2.2.dist-info/LICENSE
lkfmt-0.2.2.dist-info/METADATA
lkfmt-0.2.2.dist-info/WHEEL
lkfmt-0.2.2.dist-info/entry_points.txt
lkfmt-0.2.2.dist-info/RECORD
