Metadata-Version: 2.1
Name: lkfmt
Version: 0.2.2
Summary: All-in-one Python code formattor which is tailored of `black` + `isort` + `autoflake` for myself taste.
Home-page: https://github.com/likianta/lkfmt
License: MIT
Author: likianta
Author-email: likianta@foxmail.com
Requires-Python: >=3.8,<4.0
Classifier: License :: OSI Approved :: MIT License
Classifier: Programming Language :: Python :: 3
Classifier: Programming Language :: Python :: 3.8
Classifier: Programming Language :: Python :: 3.9
Classifier: Programming Language :: Python :: 3.10
Classifier: Programming Language :: Python :: 3.11
Requires-Dist: argsense
Requires-Dist: autoflake
Requires-Dist: black
Requires-Dist: isort
Requires-Dist: lk-logger
Requires-Dist: lk-utils
